setup.py
agh_distributions/Binomialdistribution.py
agh_distributions/Gaussiandistribution.py
agh_distributions/Generaldistribution.py
agh_distributions/__init__.py
agh_distributions.egg-info/PKG-INFO
agh_distributions.egg-info/SOURCES.txt
agh_distributions.egg-info/dependency_links.txt
agh_distributions.egg-info/not-zip-safe
agh_distributions.egg-info/top_level.txt